{"errors":[],"warnings":[],"namedChunkGroups":{"polyfill":{"chunks":[1,0,6],"assets":["webpack-runtime-c539290885951aeae249.js","webpack-runtime-c539290885951aeae249.js.map","commons-a205447ffab8713fdfcf.js","commons-a205447ffab8713fdfcf.js.map","polyfill-4e6e4b815ec2ab7eb0e2.js","polyfill-4e6e4b815ec2ab7eb0e2.js.map"],"children":{},"childAssets":{}},"app":{"chunks":[1,5,0,2],"assets":["webpack-runtime-c539290885951aeae249.js","webpack-runtime-c539290885951aeae249.js.map","framework-256fdde5199f9087be1b.js","framework-256fdde5199f9087be1b.js.map","commons-a205447ffab8713fdfcf.js","commons-a205447ffab8713fdfcf.js.map","app-3ea627e8ade59f3d319d.js","app-3ea627e8ade59f3d319d.js.map"],"children":{},"childAssets":{}},"component---src-pages-404-js":{"chunks":[0,3],"assets":["commons-a205447ffab8713fdfcf.js","commons-a205447ffab8713fdfcf.js.map","component---src-pages-404-js-f083dd6d30bd0d9d856c.js","component---src-pages-404-js-f083dd6d30bd0d9d856c.js.map"],"children":{},"childAssets":{}},"component---src-pages-index-js":{"chunks":[7,0,4],"assets":["styles.88d137c825c64c5d1620.css","styles-9411612e31e4f14527d1.js","styles-9411612e31e4f14527d1.js.map","commons-a205447ffab8713fdfcf.js","commons-a205447ffab8713fdfcf.js.map","component---src-pages-index-js-039588937c2fa19116d3.js","component---src-pages-index-js-039588937c2fa19116d3.js.map"],"children":{},"childAssets":{}}},"assetsByChunkName":{"polyfill":["webpack-runtime-c539290885951aeae249.js","commons-a205447ffab8713fdfcf.js","polyfill-4e6e4b815ec2ab7eb0e2.js"],"app":["webpack-runtime-c539290885951aeae249.js","framework-256fdde5199f9087be1b.js","commons-a205447ffab8713fdfcf.js","app-3ea627e8ade59f3d319d.js"],"component---src-pages-404-js":["commons-a205447ffab8713fdfcf.js","component---src-pages-404-js-f083dd6d30bd0d9d856c.js"],"component---src-pages-index-js":["styles.88d137c825c64c5d1620.css","styles-9411612e31e4f14527d1.js","commons-a205447ffab8713fdfcf.js","component---src-pages-index-js-039588937c2fa19116d3.js"]}}